__scratch/scratch.py
_sphinx/_source/conf.py
tests/test_new_legacy.py
tests/test_singleton.py
truewinds/__init__.py
truewinds/core.py
truewinds/legacy.py
truewinds/magdec.py
truewinds/qaqc.py
truewinds/truewinds.py
truewinds-0.0.4.dist-info/licenses/LICENSE
truewinds-0.0.4.dist-info/METADATA
truewinds-0.0.4.dist-info/WHEEL
truewinds-0.0.4.dist-info/top_level.txt
truewinds-0.0.4.dist-info/RECORD
